[
  {
    "quote": "I love gooning on Loonar"
  },
  {
    "quote": "meow :3"
  },
  {
    "quote": "abcdihjklmnopqrstuvwxyz"
  },
  {
    "quote": "We the people of the united states in order to form a more perfect pr0xxy....."
  },
  {
    "quote": "Lightsped"
  },
  {
    "quote": "Mogging other prr0xies"
  },
  {
    "quote": "https://www.youtube.com/watch?v=EvAhPPejzBQ"
  },
  {
    "quote": "Meow."
  },
  {
    "quote": "craeted buy barceat"
  },
  {
    "quote": "this is the quoteeee~"
  },
  {
    "quote": "I AM TECHNONYTE."
  },
  {
    "quote": "lunar is goober"
  },
  {
    "quote": "OH GOD PLEASE HELP"
  },
  {
    "quote": "erahs htiw sdnierf"
  },
  {
    "quote": "Prr0xy gang rise up"
  },
  {
    "quote": "Loonar is the future"
  },
  {
    "quote": "he made a statement so good even his opps praised him"
  },
  {
    "quote": "#🇯🇵Japan is turning footsteps into electricity! Using piezoelectric tiles, every step you take generates a small amount of energy. Millions of steps together can power LED lights and displays in busy places like Shibuya Station. A brilliant way to create a sustainable and smart city"
  }
]
